shoddybreak/__init__.py
shoddybreak/screen.py
shoddybreakreddit-1.1.3.dist-info/METADATA
shoddybreakreddit-1.1.3.dist-info/WHEEL
shoddybreakreddit-1.1.3.dist-info/top_level.txt
shoddybreakreddit-1.1.3.dist-info/RECORD
