Metadata-Version: 2.1
Name: shoddybreakreddit
Version: 1.1.3
Summary: A pygame based art animation library
Home-page: https://github.com/frost-dream/pygame-arts
Author: FrostDream
Author-email: frostdream3k@gmail.com
Requires-Dist: pygame
